MANIFEST.in
README.rst
requirements.txt
setup.py
pkgdependency/__init__.py
pkgdependency/dependency.py
pkgdependency/verify.py
pkgdependency.egg-info/PKG-INFO
pkgdependency.egg-info/SOURCES.txt
pkgdependency.egg-info/dependency_links.txt
pkgdependency.egg-info/entry_points.txt
pkgdependency.egg-info/requires.txt
pkgdependency.egg-info/top_level.txt
pkgdependency/scripts/__init__.py
pkgdependency/scripts/command.py