Metadata-Version: 1.1
Name: pkgdependency
Version: 1.0.4
Summary: Package Dependency: Validates package requirements
Home-page: https://github.com/gumi/pkgdependency
Author: kinpira
Author-email: yusuke.yamatani@gu3.co.jp
License: MIT
Platform: UNKNOWN
Classifier: Programming Language :: Python :: 2
Classifier: Programming Language :: Python :: 2.7
Classifier: Programming Language :: Python :: 3
Classifier: Programming Language :: Python :: 3.3
Classifier: Programming Language :: Python :: 3.4
Classifier: License :: OSI Approved :: MIT License
